packagescrape/__init__.py
packagescrape-0.9.0.dist-info/METADATA
packagescrape-0.9.0.dist-info/WHEEL
packagescrape-0.9.0.dist-info/top_level.txt
packagescrape-0.9.0.dist-info/RECORD
