Metadata-Version: 2.1
Name: packagescrape
Version: 0.9.0
Summary: PyPackageScraper is a Python library designed to make it easy to gather information and data from other Python packages.
Author: Nick
Author-email: antirat@nescher.com
Keywords: python
Classifier: Operating System :: Microsoft :: Windows
